data_augmentation_GASPLN
