Metadata-Version: 2.1
Name: data-augmentation-GASPLN
Version: 0.2.3
Summary: Data augmentation for Portuguese language
Author: Artur Melchiori Cerri
Author-email: arturmelchiori@gmail.com
License-File: LICENSE
